MANIFEST.in
README.rst
dj_settings_helpers.py
setup.py
dj_settings_helpers.egg-info/PKG-INFO
dj_settings_helpers.egg-info/SOURCES.txt
dj_settings_helpers.egg-info/dependency_links.txt
dj_settings_helpers.egg-info/not-zip-safe
dj_settings_helpers.egg-info/top_level.txt