Metadata-Version: 1.1
Name: dj-settings-helpers
Version: 1.0.0
Summary: Simple helpers for setting up your Django settings file
Home-page: https://github.com/tswicegood/dj-settings-helpers
Author: Travis Swicegood
Author-email: travis@domain51.com
License: Apache
Platform: any
Classifier: Environment :: Web Environment
Classifier: Intended Audience :: Developers
Classifier: License :: OSI Approved :: Apache Software License
Classifier: Operating System :: OS Independent
Classifier: Programming Language :: Python
Classifier: Topic :: Internet :: WWW/HTTP :: Dynamic Content
Classifier: Topic :: Software Development :: Libraries :: Python Modules
